jinni_server_pkg/__init__.py
jinni_server-0.3.0.dist-info/METADATA
jinni_server-0.3.0.dist-info/WHEEL
jinni_server-0.3.0.dist-info/entry_points.txt
jinni_server-0.3.0.dist-info/RECORD
